ovos_stt_plugin_server/__init__.py
ovos_stt_plugin_server/version.py
ovos_stt_plugin_server-0.1.3.dist-info/licenses/LICENSE
ovos_stt_plugin_server-0.1.3.dist-info/METADATA
ovos_stt_plugin_server-0.1.3.dist-info/WHEEL
ovos_stt_plugin_server-0.1.3.dist-info/entry_points.txt
ovos_stt_plugin_server-0.1.3.dist-info/top_level.txt
ovos_stt_plugin_server-0.1.3.dist-info/zip-safe
ovos_stt_plugin_server-0.1.3.dist-info/RECORD
